<?xml version="1.0" ?>
<form xmlns:xsi="http://www.w3.org/2001/XMLSchema-instance" xsi:noNamespaceSchemaLocation="urn:magento:module:Magento_Ui:etc/ui_configuration.xsd">
    <!--Set field in category section-->
    <fieldset name="search_engine_optimization">
        <field name="cat_search_engine_robots">
            <argument name="data" xsi:type="array">
                <item name="options" xsi:type="object">Neo\RobotsMetaTag\Model\Config\Source\CategoryMetaOptions</item>
                <item name="config" xsi:type="array">
                    <item name="required" xsi:type="boolean">false</item>
                    <item name="validation" xsi:type="array">
                        <item name="required-entry" xsi:type="boolean">true</item>
                    </item>
                    <item name="sortOrder" xsi:type="number">400</item>
                    <item name="dataType" xsi:type="string">string</item>
                    <item name="formElement" xsi:type="string">select</item>
                    <item name="label" translate="true" xsi:type="string">Search Engine Robots</item>
                </item>
            </argument>
        </field>
    </fieldset>
</form>